odoo9_addon_fetchmail_thread_default-9.0.1.0.0-py2.7-nspkg.pth
odoo9_addon_fetchmail_thread_default-9.0.1.0.0.dist-info/DESCRIPTION.rst
odoo9_addon_fetchmail_thread_default-9.0.1.0.0.dist-info/METADATA
odoo9_addon_fetchmail_thread_default-9.0.1.0.0.dist-info/RECORD
odoo9_addon_fetchmail_thread_default-9.0.1.0.0.dist-info/WHEEL
odoo9_addon_fetchmail_thread_default-9.0.1.0.0.dist-info/metadata.json
odoo9_addon_fetchmail_thread_default-9.0.1.0.0.dist-info/namespace_packages.txt
odoo9_addon_fetchmail_thread_default-9.0.1.0.0.dist-info/top_level.txt
odoo_addons/fetchmail_thread_default/README.rst
odoo_addons/fetchmail_thread_default/__init__.py
odoo_addons/fetchmail_thread_default/__openerp__.py
odoo_addons/fetchmail_thread_default/demo/data.xml
odoo_addons/fetchmail_thread_default/i18n/.empty
odoo_addons/fetchmail_thread_default/models/__init__.py
odoo_addons/fetchmail_thread_default/models/fetchmail_server.py
odoo_addons/fetchmail_thread_default/models/mail_thread.py
odoo_addons/fetchmail_thread_default/static/description/icon.png
odoo_addons/fetchmail_thread_default/tests/__init__.py
odoo_addons/fetchmail_thread_default/tests/test_fetchmail.py
odoo_addons/fetchmail_thread_default/views/fetchmail_server_view.xml
